paper_finder/__init__.py
paper_finder/api.py
paper_finder/download.py
paper_finder/search.py
paper_finder/utils/__init__.py
paper_finder/utils/config.py
paper_finder/utils/download.py
paper_finder/utils/get_paper_details.py
paper_finder/utils/paper_with_code_api.py
paper_finder/utils/search.py
paper_finder-0.11.dist-info/LICENSE
paper_finder-0.11.dist-info/METADATA
paper_finder-0.11.dist-info/WHEEL
paper_finder-0.11.dist-info/top_level.txt
paper_finder-0.11.dist-info/RECORD
