Metadata-Version: 2.1
Name: paper-finder
Version: 0.11
Summary: Finder papers
Home-page: https://github.com/meta-tabchen/paper-finder
Author: TabChen
Author-email: 2808581543@qq.com
License: UNKNOWN
Project-URL: Bug Tracker, https://github.com/meta-tabchen/paper-finder/issues
Platform: UNKNOWN
Classifier: Programming Language :: Python :: 3
Classifier: License :: OSI Approved :: MIT License
Classifier: Operating System :: OS Independent
Requires-Python: >=3.5
License-File: LICENSE
Requires-Dist: requests
Requires-Dist: pandas
Requires-Dist: tqdm
Requires-Dist: beautifulsoup4
